xanlib/__init__.py
xanlib/compressed_vertex.py
xanlib/face.py
xanlib/key_animation.py
xanlib/math_utils.py
xanlib/node.py
xanlib/py.typed
xanlib/scene.py
xanlib/vertex.py
xanlib/vertex_animation.py
xanlib/xbf_io.py
xanlib-0.2.0.dist-info/LICENSE
xanlib-0.2.0.dist-info/METADATA
xanlib-0.2.0.dist-info/WHEEL
xanlib-0.2.0.dist-info/RECORD
