Metadata-Version: 2.1
Name: xanlib
Version: 0.2.0
Summary: A library to handle the 3D data format XBF from the game Emperor: Battle for Dune.
Home-page: https://github.com/Lunaji/xanlib
License: MIT
Author: Lunaji
Author-email: lunacyjay@gmail.com
Requires-Python: >=3.10
Classifier: License :: OSI Approved :: MIT License
Classifier: Programming Language :: Python :: 3
Classifier: Programming Language :: Python :: 3.10
Classifier: Programming Language :: Python :: 3.11
Classifier: Programming Language :: Python :: 3.12
Classifier: Programming Language :: Python :: 3.13
